xia_authenticator/__init__.py
xia_authenticator/authenticator.cpython-39-x86_64-linux-gnu.so
xia_authenticator-0.1.4.dist-info/LICENSE.txt
xia_authenticator-0.1.4.dist-info/METADATA
xia_authenticator-0.1.4.dist-info/WHEEL
xia_authenticator-0.1.4.dist-info/top_level.txt
xia_authenticator-0.1.4.dist-info/RECORD
