Metadata-Version: 2.1
Name: xia-authenticator
Version: 0.1.4
Summary: X-I-A Authenticator
Home-page: https://develop.x-i-a.com/docs/xia-authenticator/0.1.4/index.html
Author: X-I-A
Author-email: admin@x-i-a.com
License: UNKNOWN
Platform: UNKNOWN
Requires-Python: >=3.9
License-File: LICENSE.txt
Requires-Dist: PyJWT
Requires-Dist: xia-meta-auth
